pynetmito/__init__.py
pynetmito/client.py
pynetmito/py.typed
pynetmito/schemas.py
pynetmito/types.py
pynetmito-0.2.6.dist-info/METADATA
pynetmito-0.2.6.dist-info/WHEEL
pynetmito-0.2.6.dist-info/licenses/LICENSE
pynetmito-0.2.6.dist-info/RECORD
