Metadata-Version: 2.4
Name: pynetmito
Version: 0.2.6
Summary: Python Client SDK for mitosis
Project-URL: Documentation, https://docs.stack.rs/mitosis/
Project-URL: Homepage, https://github.com/stack-rs/mitosis-python-sdk
Project-URL: Source, https://github.com/stack-rs/mitosis-python-sdk
Author-email: BobAnkh <bobankhshen@gmail.com>
License: Apache-2.0
License-File: LICENSE
Keywords: API,Async,Client,Distributed,HTTP,REST,SDK,evaluation,mitosis
Classifier: Development Status :: 3 - Alpha
Classifier: Environment :: Web Environment
Classifier: Framework :: AsyncIO
Classifier: Intended Audience :: Developers
Classifier: Intended Audience :: Science/Research
Classifier: License :: OSI Approved :: Apache Software License
Classifier: Operating System :: OS Independent
Classifier: Programming Language :: Python :: 3
Classifier: Programming Language :: Python :: 3 :: Only
Classifier: Programming Language :: Python :: 3.10
Classifier: Programming Language :: Python :: 3.11
Classifier: Programming Language :: Python :: 3.12
Classifier: Programming Language :: Python :: 3.13
Classifier: Topic :: Internet :: WWW/HTTP
Classifier: Topic :: Software Development :: Libraries :: Python Modules
Classifier: Topic :: System :: Distributed Computing
Classifier: Topic :: Utilities
Requires-Python: >=3.10
Requires-Dist: httpx>=0.28.1
Requires-Dist: platformdirs>=4.4.0
Requires-Dist: pydantic>=2.11.7
Requires-Dist: python-dateutil>=2.9.0.post0
